pyckify/__init__.py
pyckify/constants.py
pyckify/options.py
pyckify/result.py
pyckify/utils.py
pyckify-0.1.2.dist-info/LICENSE
pyckify-0.1.2.dist-info/METADATA
pyckify-0.1.2.dist-info/WHEEL
pyckify-0.1.2.dist-info/top_level.txt
pyckify-0.1.2.dist-info/RECORD
