Metadata-Version: 2.1
Name: pyckify
Version: 0.1.2
Summary: A modern interactive terminal picker for creating interactive command-line selection interfaces
Home-page: https://github.com/ReiDoBrega/pyckify
Author: ReiDoBrega
Author-email: pedro94782079@gmail.com
License: MIT
Project-URL: Homepage, https://github.com/ReiDoBrega/pyckify
Project-URL: Repository, https://github.com/ReiDoBrega/pyckify
Keywords: terminal,gui,pick,pyckify,selection,ui,rich,curses
Classifier: Programming Language :: Python :: 3
Classifier: License :: OSI Approved :: MIT License
Classifier: Operating System :: OS Independent
Requires-Python: >=3.7
License-File: LICENSE
Requires-Dist: rich>=13.0.0
Requires-Dist: windows-curses>=2.2.0; platform_system == "Windows"
